ParcialJunto.v
`timescale 1ns / 1ps


module ParcialJunto(
    input clk,
	input start,
	input  [15:0] n,	
	output reg [31:0]F
	
	
    );
    
	reg n1,n2,n3,n4,y1,y2,z1,z2,f1;
	reg [15:0] N;
	reg [15:0] Y;
	reg [31:0] Z;
	
	always @(*) 
	begin 
		if(presente==S1)
			N <= n;
		else
			N <=N;
	end

///////////////////////////////////////////////////////maquina de estados////////////////////////////////////////////////////////
    parameter S1  = 3'd0;
    parameter S2 = 3'd1;
    parameter S3 = 3'd2;
	parameter S4  = 3'd3;
	parameter S5  = 3'd4;
	parameter S6  = 3'd5;
	parameter S7  = 3'd6;
	parameter S8  = 3'd7;

    reg [2:0] presente = S1; // Registro de Estado - Valor inicial
    reg [2:0] futuro;            // Entrada del registro de Estado

    // Registro de estado 
    always @(posedge clk)
        presente <= futuro;

    // Lógica del estado siguiente
    always @(*)
        case (presente)
            S1:
                if(start==1 && N>3)
                    futuro <= S2;
                else if(start==1 && N<=3)
                    futuro <= S8;
				else
					futuro <= S1;
            S2:                
                futuro <= S3;
            S3:
				if(N!=3 && N<3)
					futuro <= S4;
				else if(N!=3 && N>3)
                    futuro <= S3;
				else if(N==3)
					futuro <= S6;
			S4:                
                futuro <= S5;
			S5:
                if(N!=5 && N>5)
                    futuro <= S5;
                else if(N!=5 && N<5)
                    futuro <= S7;
				else if(N==5)
					futuro <= S6;
			S6:
				if(Y!=3)
					futuro <= S7;
				else if(Y==3)
                    futuro <= S8;
			S7:                
                futuro <= S2;
			S8:                
                futuro <= S1;
            default:
                futuro <= S1;
        endcase
    
    // Lógica de salida
    always @(presente)
        case (presente)
            S1 : begin
                n1 <= 1'b0;
                n2 <= 1'b1;
                n3 <= 1'b1;
                n4 <= 1'b1;
                y1 <= 1'b1;
				y2 <= 1'b1;
				z1 <= 1'b1;
				z2 <= 1'b1;
				f1 <= 1'b0;
            end
            S2 : begin
                n1 <= 1'b1;
                n2 <= 1'b0;
                n3 <= 1'b1;
                n4 <= 1'b1;
                y1 <= 1'b1;
				y2 <= 1'b0;
				z1 <= 1'b0;
				z2 <= 1'b1;
				f1 <= 1'b0;
            end
            S3 : begin
                n1 <= 1'b1;
                n2 <= 1'b1;
                n3 <= 1'b0;
                n4 <= 1'b1;
                y1 <= 1'b0;
				y2 <= 1'b1;
				z1 <= 1'b0;
				z2 <= 1'b1;
				f1 <= 1'b0;
            end
			S4 : begin
                n1 <= 1'b1;
                n2 <= 1'b1;
                n3 <= 1'b1;
                n4 <= 1'b1;
                y1 <= 1'b0;
				y2 <= 1'b1;
				z1 <= 1'b0;
				z2 <= 1'b1;
				f1 <= 1'b0;
            end
			S5 : begin
                n1 <= 1'b1;
                n2 <= 1'b1;
                n3 <= 1'b1;
                n4 <= 1'b0;
                y1 <= 1'b0;
				y2 <= 1'b1;
				z1 <= 1'b0;
				z2 <= 1'b1;
				f1 <= 1'b0;
            end
			S6 : begin
                n1 <= 1'b0;
                n2 <= 1'b1;
                n3 <= 1'b1;
                n4 <= 1'b1;
                y1 <= 1'b0;
				y2 <= 1'b1;
				z1 <= 1'b1;
				z2 <= 1'b0;
				f1 <= 1'b0;
            end
			S7 : begin
                n1 <= 1'b1;
                n2 <= 1'b1;
                n3 <= 1'b1;
                n4 <= 1'b1;
                y1 <= 1'b0;
				y2 <= 1'b1;
				z1 <= 1'b0;
				z2 <= 1'b1;
				f1 <= 1'b0;
            end
			S8 : begin
                n1 <= 1'b0;
                n2 <= 1'b1;
                n3 <= 1'b1;
                n4 <= 1'b1;
                y1 <= 1'b0;
				y2 <= 1'b1;
				z1 <= 1'b0;
				z2 <= 1'b1;
				f1 <= 1'b1;
            end
            default: begin
                n1 <= 1'b0;
                n2 <= 1'b1;
                n3 <= 1'b1;
                n4 <= 1'b1;
                y1 <= 1'b1;
				y2 <= 1'b1;
				z1 <= 1'b1;
				z2 <= 1'b1;
				f1 <= 1'b0;
            end
        endcase
///////////////////////////////////////////////////////datapath//////////////////////////////////////////////////////////////////
// 1 0
    wire [15:0] nextN1;
    wire [15:0] nextN2;
	wire [15:0] nextN3;
	wire [15:0] nextN4;
	wire [15:0] nextY1;
	wire [15:0] nextY2;
	wire [31:0] nextZ1;
	wire [31:0] nextZ2;
	wire [15:0] nextF1;
	
	    
    // Registro N
    always @(posedge clk)
       N <= nextN1;
    
	assign nextN4 = (n4)? Y:N-16'd5;
	assign nextN3 = (n3)? nextN4:N-16'd3;
	assign nextN2 = (n2)? nextN3:N-16'd1;
    assign nextN1 = (n1)? nextN2:N;	
	     
    // Registro Y
    always @(posedge clk)
        Y <= nextY1;
    
	assign nextY2 = (y2)? n:N-16'd1;
    assign nextY1 = (y1)? nextY2:Y;
		
	//Registro Z
	always @(posedge clk)
        Z <= nextZ1;
		
	assign nextZ2 = (z2)? 31'd0:Z+Y;
    assign nextZ1 = (z1)? nextZ2:Z;
	
    //Registro F
	always @(posedge clk)
        F <= nextF1;
		
	assign nextF1 = (f1)? Z:F;   




    
endmodule

TB.v
`timescale 1ns / 1ps


module TB();

reg clk,reset,start;
reg [15:0] n;
wire [31:0] F;
//wire busy;

ParcialJunto AU(
	.clk(clk),
//	.reset(reset),
	.start(start),
	.n(n),
	.F(F)
	);
	

initial
begin
 clk = 1'b0;
 reset  = 1'b0 ;
 n=16'd8;
// reset=1;
 start=1;
end

always #5 clk = ~clk;

// Modulo initial
initial
begin
    #10;
    start=1;
	#500;
	n=16'd15;
	
	#2000
        $finish();
    end
	initial begin 
$dumpfile ("resultados.vcd");
$dumpvars;
end
    
endmodule

resultados.vcd
$date
	Sun Aug 14 11:22:04 2022
$end
$version
	Icarus Verilog
$end
$timescale
	1ps
$end
$scope module TB $end
$var wire 32 ! F [31:0] $end
$var reg 1 " clk $end
$var reg 16 # n [15:0] $end
$var reg 1 $ reset $end
$var reg 1 % start $end
$scope module AU $end
$var wire 1 " clk $end
$var wire 16 & n [15:0] $end
$var wire 1 % start $end
$var wire 32 ' nextZ2 [31:0] $end
$var wire 32 ( nextZ1 [31:0] $end
$var wire 16 ) nextY2 [15:0] $end
$var wire 16 * nextY1 [15:0] $end
$var wire 16 + nextN4 [15:0] $end
$var wire 16 , nextN3 [15:0] $end
$var wire 16 - nextN2 [15:0] $end
$var wire 16 . nextN1 [15:0] $end
$var wire 16 / nextF1 [15:0] $end
$var parameter 3 0 S1 $end
$var parameter 3 1 S2 $end
$var parameter 3 2 S3 $end
$var parameter 3 3 S4 $end
$var parameter 3 4 S5 $end
$var parameter 3 5 S6 $end
$var parameter 3 6 S7 $end
$var parameter 3 7 S8 $end
$var reg 32 8 F [31:0] $end
$var reg 16 9 N [15:0] $end
$var reg 16 : Y [15:0] $end
$var reg 32 ; Z [31:0] $end
$var reg 1 < f1 $end
$var reg 3 = futuro [2:0] $end
$var reg 1 > n1 $end
$var reg 1 ? n2 $end
$var reg 1 @ n3 $end
$var reg 1 A n4 $end
$var reg 3 B presente [2:0] $end
$var reg 1 C y1 $end
$var reg 1 D y2 $end
$var reg 1 E z1 $end
$var reg 1 F z2 $end
$upscope $end
$upscope $end
$enddefinitions $end
$comment Show the parameter values. $end
$dumpall
b111 7
b110 6
b101 5
b100 4
b11 3
b10 2
b1 1
b0 0
$end
#0
$dumpvars
1F
1E
1D
1C
b0 B
1A
1@
1?
0>
b1 =
0<
bx ;
bx :
b1000 9
bx 8
bx /
b1000 .
bx -
bx ,
bx +
b1000 *
b1000 )
b0 (
b0 '
b1000 &
1%
0$
b1000 #
0"
bx !
$end
#5000
b111 *
b111 .
b111 )
0E
0D
0?
1>
b10 =
b111 -
b1000 ,
b1000 +
b1 B
b1000 :
b0 ;
b0xxxxxxxxxxxxxxxx !
b0xxxxxxxxxxxxxxxx 8
1"
#10000
0"
#15000
1D
0C
0@
1?
b100 ,
b100 .
b111 *
b111 +
b100 -
b1000 )
b111 :
b111 9
b10 B
1"
#20000
0"
#25000
b1 .
b1 -
b1 ,
b100 9
1"
#30000
0"
#35000
b11 =
b1111111111111110 .
b1111111111111110 -
b1111111111111110 ,
b1 9
1"
#40000
0"
#45000
1@
b100 =
b111 .
b111 -
b111 ,
b11 B
b1111111111111110 9
1"
#50000
0"
#55000
b10 .
b10 -
b10 ,
b10 +
0A
b111 9
b100 B
1"
#60000
0"
#65000
b110 =
b1111111111111101 .
b1111111111111101 -
b1111111111111101 ,
b1111111111111101 +
b10 9
1"
#70000
0"
#75000
1A
b1 =
b111 .
b111 -
b111 ,
b111 +
b1111111111111101 9
b110 B
1"
#80000
0"
#85000
b110 .
b110 )
b110 *
b110 -
0D
1C
0?
b10 =
b1 B
b111 9
1"
#90000
0"
#95000
1D
0C
0@
1?
b11 ,
b11 .
b110 *
b110 +
b11 -
b1000 )
b110 :
b110 9
b10 B
1"
#100000
0"
#105000
b101 =
b0 .
b0 -
b0 ,
b11 9
1"
#110000
0"
#115000
b110 (
b110 '
0F
1E
1@
0>
b110 =
b0 .
b110 -
b110 ,
b0 9
b101 B
1"
#120000
0"
#125000
b110 .
1F
0E
1>
b1 =
b110 (
b0 '
b110 B
b110 ;
1"
#130000
0"
#135000
b101 .
b101 )
b101 *
b101 -
0D
1C
0?
b10 =
b110 9
b1 B
1"
#140000
0"
#145000
1D
0C
0@
1?
b10 .
b101 *
b10 ,
b10 -
b1000 )
b101 +
b10 B
b101 9
b101 :
1"
#150000
0"
#155000
b11 =
b1111111111111111 .
b1111111111111111 -
b1111111111111111 ,
b10 9
1"
#160000
0"
#165000
1@
b100 =
b101 .
b101 -
b101 ,
b11 B
b1111111111111111 9
1"
#170000
0"
#175000
b0 .
b0 -
b0 ,
b0 +
0A
b101 =
b101 9
b100 B
1"
#180000
0"
#185000
b1011 '
b1011 (
0F
1E
1A
0>
b110 =
b0 .
b101 -
b101 ,
b101 +
b101 B
b0 9
1"
#190000
0"
#195000
b101 .
1F
0E
1>
b1 =
b1011 (
b0 '
b1011 ;
b110 B
1"
#200000
0"
#205000
b100 .
b100 )
b100 *
b100 -
0D
1C
0?
b10 =
b1 B
b101 9
1"
#210000
0"
#215000
1D
0C
0@
1?
b1 ,
b1 .
b100 *
b100 +
b1 -
b1000 )
b100 :
b100 9
b10 B
1"
#220000
0"
#225000
b11 =
b1111111111111110 .
b1111111111111110 -
b1111111111111110 ,
b1 9
1"
#230000
0"
#235000
1@
b100 =
b100 .
b100 -
b100 ,
b1111111111111110 9
b11 B
1"
#240000
0"
#245000
b1111111111111111 .
b1111111111111111 -
b1111111111111111 ,
b1111111111111111 +
0A
b110 =
b100 B
b100 9
1"
#250000
0"
#255000
1A
b1 =
b100 .
b100 -
b100 ,
b100 +
b1111111111111111 9
b110 B
1"
#260000
0"
#265000
b11 .
b11 )
b11 *
b11 -
0D
1C
0?
b10 =
b1 B
b100 9
1"
#270000
0"
#275000
1D
0C
0@
1?
b101 =
b0 ,
b0 .
b11 *
b11 +
b0 -
b1000 )
b11 :
b11 9
b10 B
1"
#280000
0"
#285000
b1110 '
b1110 (
0F
1E
1@
0>
b111 =
b0 .
b11 -
b11 ,
b101 B
b0 9
1"
#290000
0"
#295000
b1110 /
1<
1F
0E
b0 =
b1110 (
b0 '
b1110 ;
b111 B
1"
#300000
0"
#305000
b0 (
b1000 *
b1000 .
0<
1E
1C
b1 =
b1000 9
b0 B
b1110 !
b1110 8
1"
#310000
0"
#315000
b111 *
b111 .
b111 )
0E
0D
0?
1>
b10 =
b111 -
b1000 ,
b1000 +
b0 ;
b1000 :
b1 B
1"
#320000
0"
#325000
1D
0C
0@
1?
b100 .
b111 *
b100 ,
b100 -
b1000 )
b111 +
b10 B
b111 9
b111 :
1"
#330000
0"
#335000
b1 .
b1 -
b1 ,
b100 9
1"
#340000
0"
#345000
b11 =
b1111111111111110 .
b1111111111111110 -
b1111111111111110 ,
b1 9
1"
#350000
0"
#355000
1@
b100 =
b111 .
b111 -
b111 ,
b1111111111111110 9
b11 B
1"
#360000
0"
#365000
b10 .
b10 -
b10 ,
b10 +
0A
b100 B
b111 9
1"
#370000
0"
#375000
b110 =
b1111111111111101 .
b1111111111111101 -
b1111111111111101 ,
b1111111111111101 +
b10 9
1"
#380000
0"
#385000
1A
b1 =
b111 .
b111 -
b111 ,
b111 +
b110 B
b1111111111111101 9
1"
#390000
0"
#395000
b110 .
b110 )
b110 *
b110 -
0D
1C
0?
b10 =
b111 9
b1 B
1"
#400000
0"
#405000
1D
0C
0@
1?
b11 .
b110 *
b11 ,
b11 -
b1000 )
b110 +
b10 B
b110 9
b110 :
1"
#410000
0"
#415000
b101 =
b0 .
b0 -
b0 ,
b11 9
1"
#420000
0"
#425000
b110 (
b110 '
0F
1E
1@
0>
b110 =
b0 .
b110 -
b110 ,
b101 B
b0 9
1"
#430000
0"
#435000
b110 .
1F
0E
1>
b1 =
b110 (
b0 '
b110 ;
b110 B
1"
#440000
0"
#445000
b101 .
b101 )
b101 *
b101 -
0D
1C
0?
b10 =
b1 B
b110 9
1"
#450000
0"
#455000
1D
0C
0@
1?
b10 ,
b10 .
b101 *
b101 +
b10 -
b1000 )
b101 :
b101 9
b10 B
1"
#460000
0"
#465000
b11 =
b1111111111111111 .
b1111111111111111 -
b1111111111111111 ,
b10 9
1"
#470000
0"
#475000
1@
b100 =
b101 .
b101 -
b101 ,
b1111111111111111 9
b11 B
1"
#480000
0"
#485000
b0 .
b0 -
b0 ,
b0 +
0A
b101 =
b100 B
b101 9
1"
#490000
0"
#495000
b1011 '
b1011 (
0F
1E
1A
0>
b110 =
b0 .
b101 -
b101 ,
b101 +
b0 9
b101 B
1"
#500000
0"
#505000
b101 .
1F
0E
1>
b1 =
b1011 (
b0 '
b110 B
b1011 ;
1"
#510000
b1111 )
0"
b1111 #
b1111 &
#515000
b100 .
b100 )
b100 *
b100 -
0D
1C
0?
b10 =
b101 9
b1 B
1"
#520000
0"
#525000
1D
0C
0@
1?
b1 .
b100 *
b1 ,
b1 -
b1111 )
b100 +
b10 B
b100 9
b100 :
1"
#530000
0"
#535000
b11 =
b1111111111111110 .
b1111111111111110 -
b1111111111111110 ,
b1 9
1"
#540000
0"
#545000
1@
b100 =
b100 .
b100 -
b100 ,
b11 B
b1111111111111110 9
1"
#550000
0"
#555000
b1111111111111111 .
b1111111111111111 -
b1111111111111111 ,
b1111111111111111 +
0A
b110 =
b100 9
b100 B
1"
#560000
0"
#565000
1A
b1 =
b100 .
b100 -
b100 ,
b100 +
b110 B
b1111111111111111 9
1"
#570000
0"
#575000
b11 .
b11 )
b11 *
b11 -
0D
1C
0?
b10 =
b100 9
b1 B
1"
#580000
0"
#585000
1D
0C
0@
1?
b101 =
b0 .
b11 *
b0 ,
b0 -
b1111 )
b11 +
b10 B
b11 9
b11 :
1"
#590000
0"
#595000
b1110 '
b1110 (
0F
1E
1@
0>
b111 =
b0 .
b11 -
b11 ,
b0 9
b101 B
1"
#600000
0"
#605000
1<
1F
0E
b0 =
b1110 (
b0 '
b111 B
b1110 ;
1"
#610000
0"
#615000
b0 (
b1111 *
b1111 .
0<
1E
1C
b1 =
b1111 9
b0 B
1"
#620000
0"
#625000
b1110 *
b1110 .
b1110 )
0E
0D
0?
1>
b10 =
b1110 -
b1111 ,
b1111 +
b1 B
b1111 :
b0 ;
1"
#630000
0"
#635000
1D
0C
0@
1?
b1011 ,
b1011 .
b1110 *
b1110 +
b1011 -
b1111 )
b1110 :
b1110 9
b10 B
1"
#640000
0"
#645000
b1000 .
b1000 -
b1000 ,
b1011 9
1"
#650000
0"
#655000
b101 .
b101 -
b101 ,
b1000 9
1"
#660000
0"
#665000
b10 .
b10 -
b10 ,
b101 9
1"
#670000
0"
#675000
b11 =
b1111111111111111 .
b1111111111111111 -
b1111111111111111 ,
b10 9
1"
#680000
0"
#685000
1@
b100 =
b1110 .
b1110 -
b1110 ,
b11 B
b1111111111111111 9
1"
#690000
0"
#695000
b1001 .
b1001 -
b1001 ,
b1001 +
0A
b1110 9
b100 B
1"
#700000
0"
#705000
b100 .
b100 -
b100 ,
b100 +
b1001 9
1"
#710000
0"
#715000
b110 =
b1111111111111111 .
b1111111111111111 -
b1111111111111111 ,
b1111111111111111 +
b100 9
1"
#720000
0"
#725000
1A
b1 =
b1110 .
b1110 -
b1110 ,
b1110 +
b110 B
b1111111111111111 9
1"
#730000
0"
#735000
b1101 .
b1101 )
b1101 *
b1101 -
0D
1C
0?
b10 =
b1110 9
b1 B
1"
#740000
0"
#745000
1D
0C
0@
1?
b1010 .
b1101 *
b1010 ,
b1010 -
b1111 )
b1101 +
b10 B
b1101 9
b1101 :
1"
#750000
0"
#755000
b111 .
b111 -
b111 ,
b1010 9
1"
#760000
0"
#765000
b100 .
b100 -
b100 ,
b111 9
1"
#770000
0"
#775000
b1 .
b1 -
b1 ,
b100 9
1"
#780000
0"
#785000
b11 =
b1111111111111110 .
b1111111111111110 -
b1111111111111110 ,
b1 9
1"
#790000
0"
#795000
1@
b100 =
b1101 .
b1101 -
b1101 ,
b1111111111111110 9
b11 B
1"
#800000
0"
#805000
b1000 .
b1000 -
b1000 ,
b1000 +
0A
b100 B
b1101 9
1"
#810000
0"
#815000
b11 .
b11 -
b11 ,
b11 +
b1000 9
1"
#820000
0"
#825000
b110 =
b1111111111111110 .
b1111111111111110 -
b1111111111111110 ,
b1111111111111110 +
b11 9
1"
#830000
0"
#835000
1A
b1 =
b1101 .
b1101 -
b1101 ,
b1101 +
b1111111111111110 9
b110 B
1"
#840000
0"
#845000
b1100 .
b1100 )
b1100 *
b1100 -
0D
1C
0?
b10 =
b1 B
b1101 9
1"
#850000
0"
#855000
1D
0C
0@
1?
b1001 ,
b1001 .
b1100 *
b1100 +
b1001 -
b1111 )
b1100 :
b1100 9
b10 B
1"
#860000
0"
#865000
b110 .
b110 -
b110 ,
b1001 9
1"
#870000
0"
#875000
b11 .
b11 -
b11 ,
b110 9
1"
#880000
0"
#885000
b101 =
b0 .
b0 -
b0 ,
b11 9
1"
#890000
0"
#895000
b1100 (
b1100 '
0F
1E
1@
0>
b110 =
b0 .
b1100 -
b1100 ,
b0 9
b101 B
1"
#900000
0"
#905000
b1100 .
1F
0E
1>
b1 =
b1100 (
b0 '
b110 B
b1100 ;
1"
#910000
0"
#915000
b1011 .
b1011 )
b1011 *
b1011 -
0D
1C
0?
b10 =
b1100 9
b1 B
1"
#920000
0"
#925000
1D
0C
0@
1?
b1000 .
b1011 *
b1000 ,
b1000 -
b1111 )
b1011 +
b10 B
b1011 9
b1011 :
1"
#930000
0"
#935000
b101 .
b101 -
b101 ,
b1000 9
1"
#940000
0"
#945000
b10 .
b10 -
b10 ,
b101 9
1"
#950000
0"
#955000
b11 =
b1111111111111111 .
b1111111111111111 -
b1111111111111111 ,
b10 9
1"
#960000
0"
#965000
1@
b100 =
b1011 .
b1011 -
b1011 ,
b11 B
b1111111111111111 9
1"
#970000
0"
#975000
b110 .
b110 -
b110 ,
b110 +
0A
b1011 9
b100 B
1"
#980000
0"
#985000
b1 .
b1 -
b1 ,
b1 +
b110 9
1"
#990000
0"
#995000
b110 =
b1111111111111100 .
b1111111111111100 -
b1111111111111100 ,
b1111111111111100 +
b1 9
1"
#1000000
0"
#1005000
1A
b1 =
b1011 .
b1011 -
b1011 ,
b1011 +
b110 B
b1111111111111100 9
1"
#1010000
0"
#1015000
b1010 .
b1010 )
b1010 *
b1010 -
0D
1C
0?
b10 =
b1011 9
b1 B
1"
#1020000
0"
#1025000
1D
0C
0@
1?
b111 .
b1010 *
b111 ,
b111 -
b1111 )
b1010 +
b10 B
b1010 9
b1010 :
1"
#1030000
0"
#1035000
b100 .
b100 -
b100 ,
b111 9
1"
#1040000
0"
#1045000
b1 .
b1 -
b1 ,
b100 9
1"
#1050000
0"
#1055000
b11 =
b1111111111111110 .
b1111111111111110 -
b1111111111111110 ,
b1 9
1"
#1060000
0"
#1065000
1@
b100 =
b1010 .
b1010 -
b1010 ,
b11 B
b1111111111111110 9
1"
#1070000
0"
#1075000
b101 .
b101 -
b101 ,
b101 +
0A
b1010 9
b100 B
1"
#1080000
0"
#1085000
b101 =
b0 .
b0 -
b0 ,
b0 +
b101 9
1"
#1090000
0"
#1095000
b10110 '
b10110 (
0F
1E
1A
0>
b110 =
b0 .
b1010 -
b1010 ,
b1010 +
b0 9
b101 B
1"
#1100000
0"
#1105000
b1010 .
1F
0E
1>
b1 =
b10110 (
b0 '
b110 B
b10110 ;
1"
#1110000
0"
#1115000
b1001 .
b1001 )
b1001 *
b1001 -
0D
1C
0?
b10 =
b1010 9
b1 B
1"
#1120000
0"
#1125000
1D
0C
0@
1?
b110 .
b1001 *
b110 ,
b110 -
b1111 )
b1001 +
b10 B
b1001 9
b1001 :
1"
#1130000
0"
#1135000
b11 .
b11 -
b11 ,
b110 9
1"
#1140000
0"
#1145000
b101 =
b0 .
b0 -
b0 ,
b11 9
1"
#1150000
0"
#1155000
b11111 '
b11111 (
0F
1E
1@
0>
b110 =
b0 .
b1001 -
b1001 ,
b0 9
b101 B
1"
#1160000
0"
#1165000
b1001 .
1F
0E
1>
b1 =
b11111 (
b0 '
b110 B
b11111 ;
1"
#1170000
0"
#1175000
b1000 .
b1000 )
b1000 *
b1000 -
0D
1C
0?
b10 =
b1001 9
b1 B
1"
#1180000
0"
#1185000
1D
0C
0@
1?
b101 .
b1000 *
b101 ,
b101 -
b1111 )
b1000 +
b10 B
b1000 9
b1000 :
1"
#1190000
0"
#1195000
b10 .
b10 -
b10 ,
b101 9
1"
#1200000
0"
#1205000
b11 =
b1111111111111111 .
b1111111111111111 -
b1111111111111111 ,
b10 9
1"
#1210000
0"
#1215000
1@
b100 =
b1000 .
b1000 -
b1000 ,
b1111111111111111 9
b11 B
1"
#1220000
0"
#1225000
b11 .
b11 -
b11 ,
b11 +
0A
b100 B
b1000 9
1"
#1230000
0"
#1235000
b110 =
b1111111111111110 .
b1111111111111110 -
b1111111111111110 ,
b1111111111111110 +
b11 9
1"
#1240000
0"
#1245000
1A
b1 =
b1000 .
b1000 -
b1000 ,
b1000 +
b110 B
b1111111111111110 9
1"
#1250000
0"
#1255000
b111 .
b111 )
b111 *
b111 -
0D
1C
0?
b10 =
b1000 9
b1 B
1"
#1260000
0"
#1265000
1D
0C
0@
1?
b100 .
b111 *
b100 ,
b100 -
b1111 )
b111 +
b10 B
b111 9
b111 :
1"
#1270000
0"
#1275000
b1 .
b1 -
b1 ,
b100 9
1"
#1280000
0"
#1285000
b11 =
b1111111111111110 .
b1111111111111110 -
b1111111111111110 ,
b1 9
1"
#1290000
0"
#1295000
1@
b100 =
b111 .
b111 -
b111 ,
b1111111111111110 9
b11 B
1"
#1300000
0"
#1305000
b10 .
b10 -
b10 ,
b10 +
0A
b100 B
b111 9
1"
#1310000
0"
#1315000
b110 =
b1111111111111101 .
b1111111111111101 -
b1111111111111101 ,
b1111111111111101 +
b10 9
1"
#1320000
0"
#1325000
1A
b1 =
b111 .
b111 -
b111 ,
b111 +
b110 B
b1111111111111101 9
1"
#1330000
0"
#1335000
b110 .
b110 )
b110 *
b110 -
0D
1C
0?
b10 =
b111 9
b1 B
1"
#1340000
0"
#1345000
1D
0C
0@
1?
b11 .
b110 *
b11 ,
b11 -
b1111 )
b110 +
b10 B
b110 9
b110 :
1"
#1350000
0"
#1355000
b101 =
b0 .
b0 -
b0 ,
b11 9
1"
#1360000
0"
#1365000
b100101 '
b100101 (
0F
1E
1@
0>
b110 =
b0 .
b110 -
b110 ,
b101 B
b0 9
1"
#1370000
0"
#1375000
b110 .
1F
0E
1>
b1 =
b100101 (
b0 '
b100101 ;
b110 B
1"
#1380000
0"
#1385000
b101 .
b101 )
b101 *
b101 -
0D
1C
0?
b10 =
b1 B
b110 9
1"
#1390000
0"
#1395000
1D
0C
0@
1?
b10 ,
b10 .
b101 *
b101 +
b10 -
b1111 )
b101 :
b101 9
b10 B
1"
#1400000
0"
#1405000
b11 =
b1111111111111111 .
b1111111111111111 -
b1111111111111111 ,
b10 9
1"
#1410000
0"
#1415000
1@
b100 =
b101 .
b101 -
b101 ,
b1111111111111111 9
b11 B
1"
#1420000
0"
#1425000
b0 .
b0 -
b0 ,
b0 +
0A
b101 =
b100 B
b101 9
1"
#1430000
0"
#1435000
b101010 '
b101010 (
0F
1E
1A
0>
b110 =
b0 .
b101 -
b101 ,
b101 +
b0 9
b101 B
1"
#1440000
0"
#1445000
b101 .
1F
0E
1>
b1 =
b101010 (
b0 '
b110 B
b101010 ;
1"
#1450000
0"
#1455000
b100 .
b100 )
b100 *
b100 -
0D
1C
0?
b10 =
b101 9
b1 B
1"
#1460000
0"
#1465000
1D
0C
0@
1?
b1 .
b100 *
b1 ,
b1 -
b1111 )
b100 +
b10 B
b100 9
b100 :
1"
#1470000
0"
#1475000
b11 =
b1111111111111110 .
b1111111111111110 -
b1111111111111110 ,
b1 9
1"
#1480000
0"
#1485000
1@
b100 =
b100 .
b100 -
b100 ,
b11 B
b1111111111111110 9
1"
#1490000
0"
#1495000
b1111111111111111 .
b1111111111111111 -
b1111111111111111 ,
b1111111111111111 +
0A
b110 =
b100 9
b100 B
1"
#1500000
0"
#1505000
1A
b1 =
b100 .
b100 -
b100 ,
b100 +
b110 B
b1111111111111111 9
1"
#1510000
0"
#1515000
b11 .
b11 )
b11 *
b11 -
0D
1C
0?
b10 =
b100 9
b1 B
1"
#1520000
0"
#1525000
1D
0C
0@
1?
b101 =
b0 .
b11 *
b0 ,
b0 -
b1111 )
b11 +
b10 B
b11 9
b11 :
1"
#1530000
0"
#1535000
b101101 '
b101101 (
0F
1E
1@
0>
b111 =
b0 .
b11 -
b11 ,
b0 9
b101 B
1"
#1540000
0"
#1545000
b101101 /
1<
1F
0E
b0 =
b101101 (
b0 '
b111 B
b101101 ;
1"
#1550000
0"
#1555000
b0 (
b1111 *
b1111 .
0<
1E
1C
b1 =
b1111 9
b101101 !
b101101 8
b0 B
1"
#1560000
0"
#1565000
b1110 *
b1110 .
b1110 )
0E
0D
0?
1>
b10 =
b1110 -
b1111 ,
b1111 +
b1 B
b1111 :
b0 ;
1"
#1570000
0"
#1575000
1D
0C
0@
1?
b1011 ,
b1011 .
b1110 *
b1110 +
b1011 -
b1111 )
b1110 :
b1110 9
b10 B
1"
#1580000
0"
#1585000
b1000 .
b1000 -
b1000 ,
b1011 9
1"
#1590000
0"
#1595000
b101 .
b101 -
b101 ,
b1000 9
1"
#1600000
0"
#1605000
b10 .
b10 -
b10 ,
b101 9
1"
#1610000
0"
#1615000
b11 =
b1111111111111111 .
b1111111111111111 -
b1111111111111111 ,
b10 9
1"
#1620000
0"
#1625000
1@
b100 =
b1110 .
b1110 -
b1110 ,
b11 B
b1111111111111111 9
1"
#1630000
0"
#1635000
b1001 .
b1001 -
b1001 ,
b1001 +
0A
b1110 9
b100 B
1"
#1640000
0"
#1645000
b100 .
b100 -
b100 ,
b100 +
b1001 9
1"
#1650000
0"
#1655000
b110 =
b1111111111111111 .
b1111111111111111 -
b1111111111111111 ,
b1111111111111111 +
b100 9
1"
#1660000
0"
#1665000
1A
b1 =
b1110 .
b1110 -
b1110 ,
b1110 +
b110 B
b1111111111111111 9
1"
#1670000
0"
#1675000
b1101 .
b1101 )
b1101 *
b1101 -
0D
1C
0?
b10 =
b1110 9
b1 B
1"
#1680000
0"
#1685000
1D
0C
0@
1?
b1010 .
b1101 *
b1010 ,
b1010 -
b1111 )
b1101 +
b10 B
b1101 9
b1101 :
1"
#1690000
0"
#1695000
b111 .
b111 -
b111 ,
b1010 9
1"
#1700000
0"
#1705000
b100 .
b100 -
b100 ,
b111 9
1"
#1710000
0"
#1715000
b1 .
b1 -
b1 ,
b100 9
1"
#1720000
0"
#1725000
b11 =
b1111111111111110 .
b1111111111111110 -
b1111111111111110 ,
b1 9
1"
#1730000
0"
#1735000
1@
b100 =
b1101 .
b1101 -
b1101 ,
b1111111111111110 9
b11 B
1"
#1740000
0"
#1745000
b1000 .
b1000 -
b1000 ,
b1000 +
0A
b100 B
b1101 9
1"
#1750000
0"
#1755000
b11 .
b11 -
b11 ,
b11 +
b1000 9
1"
#1760000
0"
#1765000
b110 =
b1111111111111110 .
b1111111111111110 -
b1111111111111110 ,
b1111111111111110 +
b11 9
1"
#1770000
0"
#1775000
1A
b1 =
b1101 .
b1101 -
b1101 ,
b1101 +
b1111111111111110 9
b110 B
1"
#1780000
0"
#1785000
b1100 .
b1100 )
b1100 *
b1100 -
0D
1C
0?
b10 =
b1 B
b1101 9
1"
#1790000
0"
#1795000
1D
0C
0@
1?
b1001 ,
b1001 .
b1100 *
b1100 +
b1001 -
b1111 )
b1100 :
b1100 9
b10 B
1"
#1800000
0"
#1805000
b110 .
b110 -
b110 ,
b1001 9
1"
#1810000
0"
#1815000
b11 .
b11 -
b11 ,
b110 9
1"
#1820000
0"
#1825000
b101 =
b0 .
b0 -
b0 ,
b11 9
1"
#1830000
0"
#1835000
b1100 (
b1100 '
0F
1E
1@
0>
b110 =
b0 .
b1100 -
b1100 ,
b0 9
b101 B
1"
#1840000
0"
#1845000
b1100 .
1F
0E
1>
b1 =
b1100 (
b0 '
b110 B
b1100 ;
1"
#1850000
0"
#1855000
b1011 .
b1011 )
b1011 *
b1011 -
0D
1C
0?
b10 =
b1100 9
b1 B
1"
#1860000
0"
#1865000
1D
0C
0@
1?
b1000 .
b1011 *
b1000 ,
b1000 -
b1111 )
b1011 +
b10 B
b1011 9
b1011 :
1"
#1870000
0"
#1875000
b101 .
b101 -
b101 ,
b1000 9
1"
#1880000
0"
#1885000
b10 .
b10 -
b10 ,
b101 9
1"
#1890000
0"
#1895000
b11 =
b1111111111111111 .
b1111111111111111 -
b1111111111111111 ,
b10 9
1"
#1900000
0"
#1905000
1@
b100 =
b1011 .
b1011 -
b1011 ,
b11 B
b1111111111111111 9
1"
#1910000
0"
